README.md
setup.cfg
setup.py
epistle/__init__.py
epistle/cli.py
epistle/epistle.py
epistle/git.py
epistle.egg-info/PKG-INFO
epistle.egg-info/SOURCES.txt
epistle.egg-info/dependency_links.txt
epistle.egg-info/entry_points.txt
epistle.egg-info/requires.txt
epistle.egg-info/top_level.txt