Metadata-Version: 2.1
Name: epistle
Version: 0.2.4
Summary: Note taking with version control
Home-page: https://github.com/msharp/epistle
Author: Max Sharples
Author-email: maxsharples@gmail.com
License: MIT
Platform: UNKNOWN
Classifier: Development Status :: 4 - Beta
Classifier: Programming Language :: Python
Classifier: Programming Language :: Python :: 3.6
Classifier: Environment :: Console
Classifier: License :: OSI Approved :: MIT License
Classifier: Topic :: Terminals
Classifier: Topic :: Text Processing
Classifier: Topic :: Utilities
